{
  "type": "mooresmod:shaped",
  "result": {
    "item": "mooresmod:division",
    "count": 1
  },
  "pattern": [
    "GBBBBB   ",
    " B B SBB ",
    " B BBB B ",
    " B     B ",
    " BBBBBBCB",
    "       B ",
    "       G ",
    "         ",
    "         "
  ],
  "key": {
    "G": {
      "item": "mooresmod:power_generator"
    },
    "B": {
      "item": "mooresmod:blustone"
    },
    "S": {
      "item": "mooresmod:subtractor"
    },
    "C": {
      "item": "mooresmod:counter"
    }
  }
}